towncrier/__init__.py
towncrier/__main__.py
towncrier/_builder.py
towncrier/_git.py
towncrier/_project.py
towncrier/_shell.py
towncrier/_version.py
towncrier/_writer.py
towncrier/build.py
towncrier/check.py
towncrier/click_default_group.py
towncrier/create.py
towncrier/_settings/__init__.py
towncrier/_settings/fragment_types.py
towncrier/_settings/load.py
towncrier/templates/default.md
towncrier/templates/default.rst
towncrier/templates/hr-between-versions.rst
towncrier/templates/single-file-no-bullets.rst
towncrier/test/__init__.py
towncrier/test/helpers.py
towncrier/test/test_build.py
towncrier/test/test_builder.py
towncrier/test/test_check.py
towncrier/test/test_create.py
towncrier/test/test_format.py
towncrier/test/test_git.py
towncrier/test/test_packaging.py
towncrier/test/test_project.py
towncrier/test/test_settings.py
towncrier/test/test_write.py
towncrier-24.7.1.dist-info/METADATA
towncrier-24.7.1.dist-info/WHEEL
towncrier-24.7.1.dist-info/entry_points.txt
towncrier-24.7.1.dist-info/licenses/LICENSE
towncrier-24.7.1.dist-info/RECORD
