Metadata-Version: 2.3
Name: towncrier
Version: 24.7.1
Summary: Building newsfiles for your project.
Project-URL: Documentation, https://towncrier.readthedocs.io/
Project-URL: Chat, https://web.libera.chat/?channels=%23twisted
Project-URL: Mailing list, https://mail.python.org/mailman3/lists/twisted.python.org/
Project-URL: Issues, https://github.com/twisted/towncrier/issues
Project-URL: Repository, https://github.com/twisted/towncrier
Project-URL: Tests, https://github.com/twisted/towncrier/actions?query=branch%3Atrunk
Project-URL: Coverage, https://codecov.io/gh/twisted/towncrier
Project-URL: Distribution, https://pypi.org/project/towncrier
License-Expression: MIT
License-File: LICENSE
Classifier: Intended Audience :: Developers
Classifier: License :: OSI Approved :: MIT License
Classifier: Operating System :: MacOS :: MacOS X
Classifier: Operating System :: Microsoft :: Windows
Classifier: Operating System :: POSIX :: Linux
Classifier: Programming Language :: Python :: 3.8
Classifier: Programming Language :: Python :: 3.9
Classifier: Programming Language :: Python :: 3.10
Classifier: Programming Language :: Python :: 3.11
Classifier: Programming Language :: Python :: 3.12
Classifier: Programming Language :: Python :: Implementation :: CPython
Classifier: Programming Language :: Python :: Implementation :: PyPy
Requires-Python: >=3.8
Requires-Dist: click
Requires-Dist: importlib-metadata>=4.6; python_version < '3.10'
Requires-Dist: importlib-resources>=5; python_version < '3.10'
Requires-Dist: jinja2
Requires-Dist: tomli; python_version < '3.11'
Provides-Extra: dev
Requires-Dist: furo>=2024.05.06; extra == 'dev'
Requires-Dist: nox; extra == 'dev'
Requires-Dist: packaging; extra == 'dev'
Requires-Dist: sphinx>=5; extra == 'dev'
Requires-Dist: twisted; extra == 'dev'
